[
    {
        "Plato": "Ceviche de pollo",
        "Ingrediente": [
            "½ de pollo en trozos",
            "Sal al gusto",
            "Pimienta al gusto",
            "3 cucharadas de aceite vegetal",
            "1 cucharada de ajo picado",
            "Ají amarillo licuado",
            "½ taza de agua",
            "¼ de cerveza rubia",
            "1 cebolla roja en juliana",
            "½ de ají amarillo en tiras",
            "Ají limo en rodajas (al gusto)",
            "Culantro picado(al gusto)",
            "¼ de taza de zumo de limón",
            "2 rocotos picados sin venas ni semillas",
            "2 tallos de cebolla china en aros",
            "2 cucharadas de agua hervida",
            "6 cucharadas de cebolla roja en cubos",
            "Limón al gusto"
        ],
        "Imagen": [
            "https://cdn.statically.io/img/www.comeperuano.pe/wp-content/uploads/2020/07/receta-ceviche-de-pollo.jpg?quality=100&f=auto"
        ]
    },
    {
        "Plato": "Seco a la nortena",
        "Ingrediente": [
            "4 presas de pollo",
            "2 zanahorias cortadas en rodajas",
            "1 cebolla picada",
            "100 gr de arverjas",
            "2 dientes de ajo picados",
            "1/2 vaso de chicha de jora",
            "100 gr de zapallo loche",
            "2  cucharadas de ají amarillo licuado",
            "2 cucharadas de ají mirasol licuado",
            "2 cucharadas de culantro picado",
            "1/2 cucharada de ají panca licuado",
            "2 cucharadas de culantro molido",
            "sal"
        ],
        "Imagen": [
            "https://cdn.statically.io/img/www.comeperuano.pe/wp-content/uploads/2020/07/receta-seco-a-la-norteña.jpg?quality=100&f=auto"
        ]
    },
    {
        "Plato": "pollo al sillao",
        "Ingrediente": [
            "cebolla china cortada en tiras",
            "1/2 kion",
            "sillao",
            "aceite de ajonjolí",
            "aceite vegetal",
            "pimienta",
            "sazonador (ajinomoto)",
            "ajo molido",
            "1 pimiento cortado en cuadrados",
            "4 presas de pollo",
            "sal al gusto",
            "chuño"
        ],
        "Imagen": [
            "https://cdn.statically.io/img/www.comeperuano.pe/wp-content/uploads/2020/07/receta-pollo-al-sillao...jpg?quality=100&f=auto"
        ]
    },
    {
        "Plato": "seco de pollo",
        "Ingrediente": [
            "1 ajo grande molido",
            "1 cebolla picada en cuadros",
            "ají amarillo con un poco de ají mirasol licuado",
            "pimienta",
            "comino",
            "sazonador (ajinomoto)",
            "aceite",
            "sal",
            "arverjas",
            "culantro licuado",
            "1/2 vaso de chicha de jora",
            "caldo de pollo",
            "2 zanahorias cortadas de en rodajas",
            "3 papas cortadas en rodajas",
            "3 presas de pollo"
        ],
        "Imagen": [
            "https://cdn.statically.io/img/www.comeperuano.pe/wp-content/uploads/2020/07/receta-seco-de-pollo..jpg?quality=100&f=auto"
        ]
    },
    {
        "Plato": "lomo saltado",
        "Ingrediente": [
            "1 kg de lomo de res o bistec",
            "2 cebollas rojas",
            "4 tomates",
            "aji amarillo",
            "1 poco de cebolla china",
            "1 cda de ajo",
            "8 cdas de vinagre",
            "4 cdas de sillao",
            "sal, pimienta y comino"
        ],
        "Imagen": [
            "https://cdn.statically.io/img/www.comeperuano.pe/wp-content/uploads/2020/08/receta-de-lomo-saltado.jpg?quality=100&f=auto"
        ]
    },
    {
        "Plato": "Arroz chaufa",
        "Ingrediente": [
            "1 kg de arroz",
            "100 gramos de cebolla china picada",
            "1 cda de ajo molido",
            "aceite vegetal",
            "1 cda de salsa de ostión",
            "Sillao",
            "Sal y pimienta",
            "Lomo fino o alguna carne de tu gusto"
        ],
        "Imagen": [
            "https://cdn.statically.io/img/www.comeperuano.pe/wp-content/uploads/2019/05/arroz-chaufa-peruano.jpg?quality=100&f=auto"
        ]
    },
    
    
    {
        "Plato": "ajiaco de olluco",
        "Ingrediente": [
            "2 cdas aceite",
            "1/2 tz cebolla picada",
            "1 cdta ajo molido",
            "3 cdas crema de aji amarillo",
            "3 tzas olluco en cubos pequeños",
            "1 tz papa blanca en cubos pequeños",
            "1 tz caldo de verduras o pollo",
            "2 cdas huacatay picado",
            "1/2 tzs queso de paria o serrano en cubos",
            "2 tzas arroz cocido",
            "4 huevos de codornis",
            "sal y pimienta"
        ],
        "Imagen": [
            "https://cdn.statically.io/img/www.comeperuano.pe/wp-content/uploads/2019/05/ajiaco-olluco-peruano.jpg?quality=100&f=auto"
        ]
    },
    {
        "Plato": "Sopa de verduras",
        "Ingrediente": [
            "1 taza de cebolla picada",
            "1 taza de poro picado",
            "aceite",
            "1 cucharada de ajo molido",
            "½ taza de apio picado",
            "½ taza de zanahoria con corte juliana",
            "½ taza de habas peladas picadas",
            "1 taza de tomate picado en dados",
            "½ nabos picado en forma de dado",
            "pimienta",
            "sal",
            "orégano",
            "agua",
            "caldo de verdura",
            "sémola",
            "papas amarillas",
            "fideos en forma de letras de abecedario",
            "limón",
            "hierbas frescas"
        ],
        "Imagen": [
            "https://cdn.statically.io/img/www.comeperuano.pe/wp-content/uploads/2020/03/SOPA-DE-VERDURAS-12.jpg?quality=100&f=auto"
        ]
    },
    {
        "Plato": "Caldo de cordero",
        "Ingrediente": [
            "1 cabeza de cordero",
            "agua",
            "mote pelado",
            "sal",
            "ají mirasol seco",
            "papas",
            "paico",
            "hierba buena",
            "rocoto molido",
            "limón",
            "cebolla china picada"
        ],
        "Imagen": [
            "https://cdn.statically.io/img/www.comeperuano.pe/wp-content/uploads/2020/05/receta-caldo-de-cordero...jpg?quality=100&f=auto"
        ]
    },
    {
        "Plato": "caldo de gallina",
        "Ingrediente": [
            "3/4 de gallina negra peruana cortada en presas (incluir el cuello, las patas, los huevitos, etc.)",
            "papas amarillas",
            "250 gr de fideo o pasta larga",
            "1 rama de apio",
            "1 zanahoria mediana",
            "1 trozo de cebolla",
            "1 trozo de kion o jengibre",
            "1 diente de ajo",
            "1 cda. de orégano",
            "sal al gusto",
            "huevos duros",
            "rocoto molido",
            "limón en rodajas",
            "cebollita china",
            "canchita serrana"
        ],
        "Imagen": [
            "https://cdn.statically.io/img/www.comeperuano.pe/wp-content/uploads/2020/04/receta-caldo-de-gallina.jpg?quality=100&f=auto"
        ]
    },
    {
        "Plato": "aguadito de pollo",
        "Ingrediente": [
            "Ingredientes del Aguadito de Pollo",
            "500 gramos de huesos de pollo",
            "½ cebolla roja picada",
            "1 cdta de ajo picado finamente",
            "2 cdas de pasta de ají amarillo",
            "4 cdas de culantro licuado",
            "1 cda de Jengibre machacado",
            "½ taza de corazones de pollo",
            "½ taza de hígados de pollo",
            "½ taza de mollejas de pollo",
            "½ taza de pescuezos y alas de pollo",
            "½ taza de arroz",
            "½ taza de arvejas",
            "½ taza de pimiento rojo",
            "½ choclo desgranado",
            "½ taza de zanahoria picada",
            "½ pechuga de pollo",
            "2 papas amarillas",
            "Sal y pimienta al gusto"
        ],
        "Imagen": [
            "https://cdn.statically.io/img/www.comeperuano.pe/wp-content/uploads/2020/04/receta-aguadito.jpg?quality=100&f=auto"
        ]
    },
    {
        "Plato": "sopa a la minuta",
        "Ingrediente": [
            "150 gr de carne molida o picada",
            "1 Tomate picado sin piel ni semillas",
            "1 cdta de Orégano",
            "sal y pimienta al gusto",
            "ajo picado",
            "3 huevos",
            "1/4 de taza de leche evaporada",
            "Cebolla roja picada en cuadritos",
            "100 gr de cabello de Ángel",
            "1 cdta de aji panca",
            "Aceite"
        ],
        "Imagen": [
            "https://cdn.statically.io/img/www.comeperuano.pe/wp-content/uploads/2020/06/sopa-a-la-minuta-peru.jpg?quality=100&f=auto"
        ]
    },
    {
        "Plato": "Chilcano de pescado",
        "Ingrediente": [
            "1 tramboyo (o cualquier otro pescado)",
            "2 cebollas cortadas a la pluma (cortes gruesos)",
            "1 tomate cortado en 4",
            "2 dientes de ajo",
            "1 trozo de kion",
            "1 hoja de laurel",
            "1 poco de culantro",
            "1/2 tz cebolla china, parte verde, picada",
            "2 cdas rocoto ,sin venas, picado",
            "4 cdas de jugo de limón",
            "sal y pimienta"
        ],
        "Imagen": [
            "https://cdn.statically.io/img/www.comeperuano.pe/wp-content/uploads/2019/05/receta-chilcano-pescado.jpg?quality=100&f=auto"
        ]
    },
    {
        "Plato": "sopa menestron",
        "Ingrediente": [
            "3 cdas de aceite",
            "½ taza de cebolla roja picada",
            "1 cda de ajo picado finamente",
            "½ taza de poro picado finamente",
            "2 litros de agua",
            "600 gramos de pecho de res",
            "½ taza de zapallo en trozos",
            "¼ de taza de Pallares frescos",
            "¼ de taza de zanahoria picada",
            "¼ de taza de frejoles frescos",
            "1 choclo en rodajas",
            "¼ de taza de alverjas",
            "1 taza y media de hojas de albahaca",
            "20 gramos de queso parmesano",
            "Aceite de Oliva al gusto",
            "Sal al gusto"
        ],
        "Imagen": [
            "https://cdn.statically.io/img/www.comeperuano.pe/wp-content/uploads/2020/06/receta-sopa-menestron.jpg?quality=100&f=auto"
        ]
    },
    {
        "Plato": "Sopa de paico",
        "Ingrediente": [
            "queso fresco o quesillo",
            "perejil",
            "huacatay",
            "paico",
            "3 huevos",
            "2 ramas hierbabuena",
            "2 ramas culantro",
            "papa blanca o papa amarilla picada",
            "sal",
            "1/2 cucharada de pasta de ajo",
            "agua"
        ],
        "Imagen": [
            "https://cdn.statically.io/img/www.comeperuano.pe/wp-content/uploads/2020/05/receta-sopa-de-paico.jpg?quality=100&f=auto"
        ]
    },
    {
        "Plato": "Sopa criolla",
        "Ingrediente": [
            "1 cebolla roja",
            "Una pizca de sal",
            "1 cucharada de ajo",
            "600 gramos de carne de res",
            "Comino a gusto",
            "2 cucharadas de ají panca",
            "3 cucharadas de pasta de tomate",
            "1 cucharada de orégano seco",
            "4 unidades de tomate",
            "5 tazas de caldo de carne",
            "Pimienta a gusto",
            "125 gramos de cabello de ángel",
            "Leche evaporada a gusto"
        ],
        "Imagen": [
            "https://cdn.statically.io/img/www.comeperuano.pe/wp-content/uploads/2020/01/sopa-criolla-receta.jpg?quality=100&f=auto"
        ]
    },
    {
        "Plato": "sopa de moron",
        "Ingrediente": [
            "sal al gusto",
            "1/2 taza de habas peladas y partidas en 2",
            "1 cebolla pequeña con corte juliana",
            "200 gr de queso fresco picado en cuadrados",
            "2 zanahorias medianas picadas en bastones",
            "130 gr de morón partido",
            "3/4 de taza de leche",
            "3 huevos",
            "1 rama de huacatay",
            "1 rama de culantro",
            "agua"
        ],
        "Imagen": [
            "https://cdn.statically.io/img/www.comeperuano.pe/wp-content/uploads/2020/08/receat-sopa-de-moron.jpg?quality=100&f=auto"
        ]
    },
    {
        "Plato": "sopa fuchifu",
        "Ingrediente": [
            "2 cucharada de jenjibre picado",
            "agua",
            "200 gr de huesos de pollo",
            "4 tallos de cebolla china",
            "500 gr de huesos de cerdo",
            "500 gr de huesos de pollo",
            "150 gr de col china",
            "4 cucharadas de fécula de papa disuelta en agua",
            "2 claras de huevo",
            "1 cucharada de cebolla china picada",
            "sal al gusto"
        ],
        "Imagen": [
            "https://cdn.statically.io/img/www.comeperuano.pe/wp-content/uploads/2020/10/receta-sopa-fuchifu.jpg?quality=100&f=auto"
        ]
    },
    {
        "Plato": "Sopa de mondongo",
        "Ingrediente": [
            "450 gr de mondongo limpio",
            "3 litros de agua",
            "200 gr cebolla blanca picada",
            "4 dientes de ajo",
            "50 gr culantro picado",
            "3 tallos de culantro",
            "200 gr de yuca cortada en trozos",
            "2 choclos cortados en rodajas",
            "1 cucharada de cebolla blanca picada"
        ],
        "Imagen": [
            "https://cdn.statically.io/img/www.comeperuano.pe/wp-content/uploads/2020/10/receta-sopa-de-mondongo...jpg?quality=100&f=auto"
        ]
    },
    {
        "Plato": "Inchicapi de gallina",
        "Ingrediente": [
            "800 gr de gallina en presas",
            "80 gr de harina de maíz disuelta en 1 taza de agua fría",
            "2 yucas peladas y cortadas por la mitad",
            "120 gr de maní sin cascar y previamente remojado",
            "10 hojas de sacha culantro",
            "2 dientes de ajos",
            "1/2 cebolla roja cortada en gajos",
            "sal al gusto",
            "2 1/2 lt de agua para el caldo",
            "1 taza de agua para el licuado"
        ],
        "Imagen": [
            "https://cdn.statically.io/img/www.comeperuano.pe/wp-content/uploads/2020/10/receta-Inchicapi-de-gallina....jpg?quality=100&f=auto"
        ]
    },
    {
        "Plato": "patasca",
        "Ingrediente": [
            "500 gr de mote seco",
            "5.5 lts de agua",
            "250 gr de mondongo",
            "3 ramas de hierbabuena",
            "hierbabuena picada",
            "1 taza de leche evaporada",
            "1 kg de pata de res o chancho",
            "1 kg de pecho de res",
            "sal al gusto",
            "cebolla china picada",
            "culantro picado"
        ],
        "Imagen": [
            "https://cdn.statically.io/img/www.comeperuano.pe/wp-content/uploads/2020/08/receta-de-patasca.jpg?quality=100&f=auto"
        ]
    },
    {
        "Plato": "Sopa de semola",
        "Ingrediente": [
            "2 lt de agua",
            "2 dientes de ajo",
            "1/2 cucharadita de sal",
            "600 gr de carne para asado cortado en tiras",
            "1 choclo cortado en rodajas",
            "300 gr de zapallo macre cortado en bastones",
            "1 zanahoria cortada en bastones",
            "100 gr de poro picado en tiras",
            "2 papas blancas cortadas en rodajas o picadas en trozos",
            "1/2 taza de arvejas",
            "1/2 taza de sémola",
            "sal al gusto",
            "orégano al gusto"
        ],
        "Imagen": [
            "https://cdn.statically.io/img/www.comeperuano.pe/wp-content/uploads/2020/10/receta-sopa-de-semola...jpg?quality=100&f=auto"
        ]
    },
    {
        "Plato": "Sopa de chairo",
        "Ingrediente": [
            "1 kilo de carne de cordero",
            "2 zanahorias picadas en trozos",
            "1 cebolla picada",
            "1 ajo picado",
            "2 rama de apio picados",
            "1 choclo cortado en rodajas",
            "1 rama de poro picada",
            "10 chuños negros, remojados un día antes pelados, desmenuzados",
            "1/taza de trigo pelado y sancochado",
            "3 papas blancas cortadas en trozos",
            "½ taza de arvejas",
            "1 taza de zapallo en cubos",
            "½ taza de habas",
            "culantro picado al gusto",
            "sal",
            "1/2 cucharadita de comino",
            "1 rama de hierbabuena"
        ],
        "Imagen": [
            "https://cdn.statically.io/img/www.comeperuano.pe/wp-content/uploads/2020/10/receta-sopa-chairo.jpg?quality=100&f=auto"
        ]
    },
    {
        "Plato": "sopa de lentejas",
        "Ingrediente": [
            "1 taza de lentejas remojadas",
            "7 taza de agua",
            "1/2 cebolla picada",
            "1 taza de vegetales mixtos (zanahoria picada – vainita picada y arvejas)",
            "1 papa picada en cuadritos",
            "1 cucharada de ají amarillo",
            "1/2 cucharadita de comino",
            "1/2 cucharadita de orégano",
            "1 cucharada de ají panca",
            "2 dientes de ajo picado",
            "1/2 cucharadita pimienta negra",
            "2 cucharadas de aceite"
        ],
        "Imagen": [
            "https://cdn.statically.io/img/www.comeperuano.pe/wp-content/uploads/2020/10/receta-sopa-de-lentejas.jpg?quality=100&f=auto"
        ]
    },
    {
        "Plato": "cazuela de res",
        "Ingrediente": [
            "¾ de taza de arroz",
            "1 cebolla blanca mediana picada",
            "½ kg papa picada en dados",
            "1 taza de zanahorias picada en dados",
            "1 taza de zapallo picada en dados",
            "1 taza vainitas picadas",
            "3 ramas de apio picados",
            "½ cucharadita de comino",
            "sal al gusto",
            "1 cucharada de ají panca en pasta",
            "1 kg carne de res cortada en trozos",
            "2 choclos cortados en rodajas",
            "1 taza de arvejas",
            "1/2 unidad de poro rallado",
            "2 cucharadas de mantequilla",
            "3 dientes de ajo picados",
            "½ cucharadita de pimienta",
            "perejil picado",
            "1 chorro de aceite",
            "1 litro de agua"
        ],
        "Imagen": [
            "https://cdn.statically.io/img/www.comeperuano.pe/wp-content/uploads/2020/10/receta-cazuela-de-res.jpg?quality=100&f=auto"
        ]
    },
    {
        "Plato": "chaque arequipeno",
        "Ingrediente": [
            "4 costillas de res",
            "2 1/2 litro de agua hervida caliente",
            "1/2 kilo de tripas lavadas",
            "1 cucharada de cebolla cortada en cuadritos",
            "1/4 de patasca de trigo precocida",
            "1 choclo en rodajas",
            "1 cucharada de aceite",
            "4 papas aplastadas",
            "3 zanahorias aplastadas",
            "1/2 repollo picado sin venas",
            "1/4 de chuño negro en trozos pequeños",
            "2 cucharadas de ají panca molido",
            "2 dientes de ajo finamente picados",
            "1 ramita de apio picado",
            "1 rama de hierbabuena",
            "1 cucharadita de orégano",
            "2 cucharadas de poro picado",
            "culantro picado al gusto",
            "perejil picado al gusto",
            "pimienta al gusto",
            "sal al gusto",
            "aceite",
            "zapallo en trozos al gusto",
            "1 puñado de habas verdes"
        ],
        "Imagen": [
            "https://cdn.statically.io/img/www.comeperuano.pe/wp-content/uploads/2020/10/receta-chaque-arequino-1.jpg?quality=100&f=auto"
        ]
    },
    {
        "Plato": "Tallarines con pollo",
        "Ingrediente": [
            "4 presas de pollo",
            "sal",
            "pimienta",
            "2 tazas de cebollas roja picada",
            "2 cucharadas de ajo molido",
            "¼ de taza ají panca molido",
            "2 de tazas de tomate licuado",
            "1 taza de zanahoria rallada",
            "2 hojas de laurel",
            "1 hongo seco",
            "Arvejas",
            "Fideos cocidos"
        ],
        "Imagen": [
            "https://cdn.statically.io/img/www.comeperuano.pe/wp-content/uploads/2020/03/tallarines-con-pollo-2.jpg?quality=100&f=auto"
        ]
    },
    {
        "Plato": "Estofado de pollo",
        "Ingrediente": [
            "8 trozos de pollo",
            "aceite",
            "sal",
            "pimienta",
            "1 tazas de cebolla roja picada",
            "1 cucharada de ajo molido",
            "¼ de taza de ají panca licuado",
            "2 tazas de tomate licuado",
            "1 pimiento",
            "1 zanahoria",
            "pasta de tomate",
            "1 hongo seco",
            "hoja de laurel",
            "comino",
            "vino",
            "Papas en rodaja",
            "Arvejas",
            "½ taza de pasas",
            "Perejil picado"
        ],
        "Imagen": [
            "https://cdn.statically.io/img/www.comeperuano.pe/wp-content/uploads/2020/03/ESTOFADO11.jpg?quality=100&f=auto"
        ]
    },
    {
        "Plato": "Olluquito con carne",
        "Ingrediente": [
            "Aceite",
            "cebolla roja picada",
            "ajo molido",
            "¼ taza de ají panca licuado",
            "¼ de ají amarillo licuado",
            "sal",
            "pimienta",
            "comino",
            "200 gr de carne de bisteck de res",
            "4 tazas de ollucos cortadas en forma de palillos delgados",
            "una taza de papa cortada palillos",
            "perejil",
            "rocoto"
        ],
        "Imagen": [
            "https://cdn.statically.io/img/www.comeperuano.pe/wp-content/uploads/2020/03/olluquito-111.jpg?quality=100&f=auto"
        ]
    },
    {
        "Plato": "escabeche de pescado",
        "Ingrediente": [
            "4 filetes de pescado (el pescado que desees)",
            "Sal, pimienta, comino",
            "Ajo molido",
            "1/4 aji mirasol licuado",
            "1/4 taza de aji amarillo licuado",
            "1/4 de aji panca",
            "1 rama de oregano y granos de pimienta.",
            "cebollas rojas",
            "Vinagre de Vino tinto"
        ],
        "Imagen": [
            "https://cdn.statically.io/img/www.comeperuano.pe/wp-content/uploads/2020/03/escabeche-de-pescado-peruano.jpg?quality=100&f=auto"
        ]
    },
    {
        "Plato": "Arroz a la jardinera",
        "Ingrediente": [
            "aceite",
            "1 taza de cebolla roja picada",
            "1 cucharada de ajo molido",
            "¼ de taza de ají amarillo licuado",
            "1 taza de tomate licuado",
            "sal",
            "pimienta",
            "comino",
            "palillo",
            "culantro picado",
            "½ taza de arvejas",
            "½ taza de vainatas en trozos",
            "½ taza de corazones de alcachofa en trozos",
            "½ taza de pimientos en dados",
            "½ taza de choclo desgranado",
            "½ taza de pallar verde",
            "½ taza de nabo en dados",
            "cerveza",
            "caldo de verduras",
            "2 tazas de arroz",
            "½ taza de ají amarillo en tiras"
        ],
        "Imagen": [
            "https://cdn.statically.io/img/www.comeperuano.pe/wp-content/uploads/2020/03/receta-de-arroz-a-la-jardinera.jpg?quality=100&f=auto"
        ]
    },
    {
        "Plato": "Milanesa de carne",
        "Ingrediente": [
            "lomo bicteck",
            "sal",
            "pimienta",
            "pan",
            "huevos",
            "mantequilla"
        ],
        "Imagen": [
            "https://d1kxxrc2vqy8oa.cloudfront.net/wp-content/uploads/2019/04/04092603/RFB-2503-3-milanesadecarne.jpg"
        ]
    },
    {
        "Plato": "Bistec con papas",
        "Ingrediente": [
            "papas blancas o amarillas",
            "bistec de lomo",
            "ajo molido",
            "sal",
            "comino",
            "pimienta negra molida",
            "aceite",
            "pisco",
            "vino tinto",
            "perejil picado",
            "caldo",
            "mantequilla"
        ],
        "Imagen": [
            "https://cdn.statically.io/img/www.comeperuano.pe/wp-content/uploads/2020/03/receta-bistec-con-papas.jpg?quality=100&f=auto"
        ]
    },
    {
        "Plato": "Estofado de carne",
        "Ingrediente": [
            "1 kg de carne de res para estofado",
            "sal",
            "pimienta",
            "aceite",
            "1 taza de cebolla roja cortada en dados",
            "½ taza de pimiento rojo picado",
            "1 cucharada de ajo molido",
            "2 cucharadas de ají panca licuado",
            "1 cucharada de ají amarillo licuado",
            "1 taza de tomate licuado",
            "vino tinto",
            "orégano",
            "comino en polvo",
            "rama de romero",
            "2 ramas de perejil",
            "1 hoja de laurel",
            "agua",
            "1 zanahoria grande cortada en rodajas",
            "1 taza de arvejas tiernas",
            "4 papas amarillas cortadas en dos",
            "2 cucharadas de pasas negras"
        ],
        "Imagen": [
            "https://cdn.statically.io/img/www.comeperuano.pe/wp-content/uploads/2020/04/receta-estofado-de-carne.jpg?quality=100&f=auto"
        ]
    },
    {
        "Plato": "pescado frito",
        "Ingrediente": [
            "4 unidades de Filetes de Pescado si se trata de un pescado grande.",
            "4 pescados enteros si es un pescado más pequeño.",
            "1  Taza Harina de maíz o pan rallado",
            "1 taza de harina de trigo",
            "2 huevos",
            "1 taza Aceite vegetal",
            "1 pizca Pimienta",
            "Sal al gusto"
        ],
        "Imagen": [
            "https://cdn.statically.io/img/www.comeperuano.pe/wp-content/uploads/2020/04/receta-pescado-frito-1.jpg?quality=100&f=auto"
        ]
    },
    {
        "Plato": "Frejolada",
        "Ingrediente": [
            "1/2 kg de frejol canario,panamito o caballero",
            "agua",
            "1 trozo de papada de cerdo",
            "1 cebolla roja cortada en cuadros",
            "1 trozo de costilla ahumada de cerdo",
            "1 trozo de cola ahumada de cerdo",
            "patitas de cerdo",
            "sal",
            "pimienta blanca",
            "aceite de oliva",
            "ajo molido",
            "una gotas de vinagre (opcional)"
        ],
        "Imagen": [
            "https://cdn.statically.io/img/www.comeperuano.pe/wp-content/uploads/2020/04/receta-frejolada..jpg?quality=100&f=auto"
        ]
    },
    {
        "Plato": "patarashca peruana",
        "Ingrediente": [
            "Seis pescados medianos enteros",
            "Cinco dientes de ajo molido",
            "Cuatro ajíes dulces o verdes",
            "Sal a gusto",
            "Seis hojas de bijao",
            "Dos cebollas",
            "Culantro de monte",
            "Un octavo de taza de aceite",
            "Media cucharadita de pimienta",
            "Una cucharadita de comino"
        ],
        "Imagen": [
            "https://cdn.statically.io/img/www.comeperuano.pe/wp-content/uploads/2020/04/patarashca-peruana.jpg?quality=100&f=auto"
        ]
    },
    {
        "Plato": "Chupe de pescado",
        "Ingrediente": [
            "4 trozos de pescado",
            "1/2 taza aceite",
            "1 taza de cebolla picada",
            "4 dientes de ajos picados",
            "1 tomate picado sin piel ni pepas",
            "2 litros caldo de pescado",
            "1/2 taza de arroz",
            "1/2 kilo de papa blanca pelada y cortada por la mitad",
            "1 choclo en rodajas",
            "1 taza habas verdes",
            "1 taza de col en trozos",
            "1 taza de zapallo en cubos",
            "1/2 taza huacatay picado",
            "5 huevos",
            "1 taza de leche evaporada",
            "1/2 kilo de queso fresco desmenuzado",
            "Pimienta al gusto",
            "Sal al gusto"
        ],
        "Imagen": [
            "https://cdn.statically.io/img/www.comeperuano.pe/wp-content/uploads/2020/04/receta-chupe-de-pescado.jpg?quality=100&f=auto"
        ]
    },
    {
        "Plato": "Seco de pescado",
        "Ingrediente": [
            "ajo molido",
            "cebolla roja picada",
            "ají amarillo licuado",
            "1 taza de culantro licuado",
            "chicha de jora",
            "1 zanahoria cortada en rodajas",
            "1/2 taza de arvejas crudas",
            "caldo de pescado",
            "papas blancas crudas cortadas en cubos medianos",
            "4 trozos de filete de pescado",
            "limon",
            "sal",
            "pimienta",
            "comino",
            "ají limo"
        ],
        "Imagen": [
            "https://cdn.statically.io/img/www.comeperuano.pe/wp-content/uploads/2020/05/receta-seco-de-pescado.jpg?quality=100&f=auto"
        ]
    },
    {
        "Plato": "Adobo de pescado",
        "Ingrediente": [
            "4 trozos de filete de pescado",
            "sal",
            "pimienta",
            "comino",
            "ajo molido",
            "orégano",
            "vinagre",
            "aceite",
            "1/4 de taza de ají panca licuado",
            "2 cebollas rojas cortadas en tiras gruesas"
        ],
        "Imagen": [
            "https://cdn.statically.io/img/www.comeperuano.pe/wp-content/uploads/2020/05/receta-adobo-de-pescado.jpg?quality=100&f=auto"
        ]
    },
    {
        "Plato": "Menestron rojo",
        "Ingrediente": [
            "2 cebollas rojas picadas",
            "1 cebolla blanca picada",
            "1 cucharada de ajo molido",
            "2 cucharadas de ají mirasol licuado",
            "2 cucharadas de pasta de tomate",
            "2 tazas de tomates licuados",
            "comino",
            "1 rama de romero",
            "1 hoja de laurel",
            "perejil",
            "culantro",
            "albahaca",
            "sal",
            "pimienta",
            "azúcar",
            "1 taza de frejoles verdes",
            "1 taza de pallares verdes",
            "1 taza de col picado",
            "1 taza de zanahoria picado en dados",
            "1 taza de apio picado en dados",
            "1 taza de nabo picado en dados",
            "1 taza de arvejas",
            "1 taza de yuca picado en dados",
            "1 pecho de pollo",
            "fideos corbata cocidos",
            "1 chorro aceite oliva",
            "queso parmesano"
        ],
        "Imagen": [
            "https://cdn.statically.io/img/www.comeperuano.pe/wp-content/uploads/2020/05/receta-menestron-rojo.jpg?quality=100&f=auto"
        ]
    },
    {
        "Plato": "Asado a la olla",
        "Ingrediente": [
            "1/4 de taza de sal",
            "2 Lt de agua",
            "carne en corte de asado de pejerrey",
            "aceite",
            "1 cebolla roja picada",
            "1 cebolla blanca picada",
            "1 cucharada de ajo molido",
            "2 cucharadas de ají panca licuado",
            "1 zanahoria rayada",
            "1 pimiento rojo",
            "4 tomates",
            "vino",
            "1 hoja de laurel",
            "1 rama de romero",
            "1 rama de perejil",
            "orégano",
            "comino"
        ],
        "Imagen": [
            "https://cdn.statically.io/img/www.comeperuano.pe/wp-content/uploads/2020/05/receta-asado-a-la-olla...jpg?quality=100&f=auto"
        ]
    },
    {
        "Plato": "Higado frito",
        "Ingrediente": [
            "1 hígado cortado en filetes",
            "sal",
            "pimienta",
            "vinagre",
            "ajo molido",
            "comino",
            "limón",
            "harina",
            "huevo",
            "pan rayado",
            "aceite"
        ],
        "Imagen": [
            "https://cdn.statically.io/img/www.comeperuano.pe/wp-content/uploads/2020/05/receta-higado-frito.jpg?quality=100&f=auto"
        ]
    },
    {
        "Plato": "Tacu tacu",
        "Ingrediente": [
            "ajo molido",
            "cebolla roja picada",
            "ají amarillo licuado",
            "1/2 taza de lentejas cocidas",
            "1 taza de lentejas licuadas",
            "1 taza de arroz blanco cocido",
            "sal",
            "pimienta",
            "comino",
            "aceite de oliva"
        ],
        "Imagen": [
            "https://cdn.statically.io/img/www.comeperuano.pe/wp-content/uploads/2020/05/receta-tacu-tacu-de-lentejas...jpg?quality=100&f=auto"
        ]
    },
    {
        "Plato": "Pescado enlochado",
        "Ingrediente": [
            "aceite",
            "1 cebolla roja picada",
            "1 cucharada de ajo molido",
            "2 cucharadas de ají amarillo licuado",
            "1 taza de loche rayado con cascara",
            "sal",
            "pimienta",
            "comino",
            "culantro picado",
            "arvejas",
            "chicha de jora",
            "agua o caldo",
            "1 loche entero",
            "yucas cocidas y picadas en dados",
            "filetes de pescado picado en dados"
        ],
        "Imagen": [
            "https://cdn.statically.io/img/www.comeperuano.pe/wp-content/uploads/2020/05/receta-pescado-enlochado.....jpg?quality=100&f=auto"
        ]
    },
    {
        "Plato": "Chicharron de chancho",
        "Ingrediente": [
            "1/2 KG de chancho trozado",
            "3 cucharadas de ajo molido",
            "sal",
            "ajinomoto",
            "aceite",
            "agua",
            "4 a 3 ramas de hierba buena"
        ],
        "Imagen": [
            "https://cdn.statically.io/img/www.comeperuano.pe/wp-content/uploads/2020/05/receta-chicharron-de-chancho...jpg?quality=100&f=auto"
        ]
    },
    {
        "Plato": "Sancochado",
        "Ingrediente": [
            "agua",
            "2 kg de carne de punta de pecho de res",
            "4 zanahorias grandes peladas y cortadas en 2",
            "4 poros",
            "4 tallos de apio",
            "1 nabo pelado y cortado en 2",
            "4 rodajas de zapallo grandes",
            "2 papas blancas grandes peladas y cortadas en 2",
            "4 trozos de yuca amarilla peladas",
            "1/4 de col",
            "2 camotes",
            "2 choclos",
            "sal",
            "pimienta blanca"
        ],
        "Imagen": [
            "https://cdn.statically.io/img/www.comeperuano.pe/wp-content/uploads/2020/05/receta-sancochado....jpg?quality=100&f=auto"
        ]
    },
    {
        "Plato": "Arverjitas partidas",
        "Ingrediente": [
            "1 tomate picado en cuadritos",
            "1 cebolla picada en cuadros",
            "pimienta",
            "comino",
            "sazonador (ajinomoto)",
            "sal",
            "ajo molido",
            "aceite vegetal",
            "caldo de carne",
            "arvejas partidas"
        ],
        "Imagen": [
            "https://cdn.statically.io/img/www.comeperuano.pe/wp-content/uploads/2020/05/receta-arvejas-partidas.jpg?quality=100&f=auto"
        ]
    },
    {
        "Plato": "Pollada",
        "Ingrediente": [
            "2 cucharadas de",
            "2 cucharadas de",
            "2 cucharadas de sillao",
            "1/4 de taza de cerveza",
            "sal",
            "4",
            "pimienta",
            "2 limones",
            "aceite"
        ],
        "Imagen": [
            "https://cdn.statically.io/img/www.comeperuano.pe/wp-content/uploads/2020/06/receta-pollada.jpg?quality=100&f=auto"
        ]
    },
    {
        "Plato": "Salpicon de pollo",
        "Ingrediente": [
            "200 gramos de brócoli",
            "100 gramos de vainitas",
            "1 cda de sal",
            "1 zanahoria en bastones",
            "100 gramos de alverjas",
            "2 papas blancas en cubos",
            "1 choclo desgranado",
            "Mayonesa",
            "Sal al gusto",
            "Limón al gusto",
            "Pimienta al gusto",
            "1 pechuga de pollo desmenuzada",
            "Lechuga",
            "Quinua cocida",
            "pimiento rojo"
        ],
        "Imagen": [
            "https://cdn.statically.io/img/www.comeperuano.pe/wp-content/uploads/2020/06/receta-de-salpicon-pollo.jpg?quality=100&f=auto"
        ]
    },
    {
        "Plato": "Pescado a la chorrillana",
        "Ingrediente": [
            "5 filete de pescados de cualquier tipo",
            "1 cebolla cortada en tiras",
            "3 tomates sin pepas cortado en tiras",
            "jugo de limón",
            "2 ají amarillos o pimiento cortado en tiras",
            "3 cucharadas de perejil picado",
            "1 cucharada de ajo molido",
            "pimienta",
            "sal",
            "harina sin preparar",
            "aceite",
            "2 cucharadas de vinagre",
            "5 cucharadas de agua"
        ],
        "Imagen": [
            "https://cdn.statically.io/img/www.comeperuano.pe/wp-content/uploads/2020/07/receta-pescado-a-la-chorrillana.jpg?quality=100&f=auto"
        ]
    },
    {
        "Plato": "Chancho al horno",
        "Ingrediente": [
            "6 Kg de carne de chancho (pierna o panceta)",
            "1/2 taza de ají panca molido",
            "3 cucharadas de ají amarillo mirasol molido",
            "ají amarillo fresco molido",
            "3 cucharadas de pimienta",
            "3 cucharadas de comino",
            "sal al gusto",
            "1 cucharada de sazonador",
            "3 cucharadas de sillao",
            "1 taza y media de vinagre tinto o vino",
            "4 cucharadas de ajo molido",
            "100 gr de mantequilla en trozos",
            "2 ramas de romero",
            "3 cucharadas de orégano",
            "1 taza de pisco",
            "tomillo"
        ],
        "Imagen": [
            "https://cdn.statically.io/img/www.comeperuano.pe/wp-content/uploads/2020/07/receta-chancho-al-horno.jpg?quality=100&f=auto"
        ]
    },
    {
        "Plato": "Chancho a cilindro",
        "Ingrediente": [
            "6 kg de costillar de chancho",
            "350 ml de vinagre",
            "3 cucharada de sal marina o la de tu preferencia",
            "5 tazas de agua"
        ],
        "Imagen": [
            "https://cdn.statically.io/img/www.comeperuano.pe/wp-content/uploads/2020/07/receta-chancho-al-cilindro-..jpg?quality=100&f=auto"
        ]
    },
    {
        "Plato": "Olluquito con pollo",
        "Ingrediente": [
            "1 kg de olluquito picado en tiras",
            "½ kg de pollo picado",
            "6 cucharadas de ají panca licuado",
            "1",
            "4 cucharadas de aceite",
            "sal",
            "pimienta",
            "comino",
            "350 ml de agua",
            "3 cucharadas de perejil picado"
        ],
        "Imagen": [
            "https://cdn.statically.io/img/www.comeperuano.pe/wp-content/uploads/2020/07/receta-olluquito-con-pollo.jpg?quality=100&f=auto"
        ]
    },
    {
        "Plato": "Guiso de lentejas",
        "Ingrediente": [
            "1/2 kilo de lentejas",
            "Ajo molido",
            "1 cebolla roja picada",
            "Pasta de tomate",
            "Sal, pimienta, comino, laurel",
            "Tocino fino",
            "Zanahoria",
            "Aceite de oliva",
            "1/2 kg de arroz"
        ],
        "Imagen": [
            "https://cdn.statically.io/img/www.comeperuano.pe/wp-content/uploads/2019/05/Receta-guiso-de-lentejas.jpg?quality=100&f=auto"
        ]
    },
    {
        "Plato": "pure de papas",
        "Ingrediente": [
            "mantequilla",
            "1 tarro de leche",
            "16 papas amarillas",
            "1 cucharada de ajo molido",
            "sal",
            "pimienta",
            "comino",
            "1/2 cucharada de aceite"
        ],
        "Imagen": [
            "https://cdn.statically.io/img/www.comeperuano.pe/wp-content/uploads/2020/08/receta-pure-de-papas.jpg?quality=100&f=auto"
        ]
    },
    {
        "Plato": "Vainita saltada",
        "Ingrediente": [
            "400 gr de vainitas",
            "agua",
            "4 cucharadas de aceite vegetal",
            "500 gr de carne salpimentada o carne de pollo picado en cuadros",
            "2 cucharaditas de ajo",
            "1 1/2 cucharadas de ají panca",
            "2 unidades de tomate",
            "1/2 taza de caldo de carne",
            "sal al gusto",
            "1/4 de cucharadita de comino",
            "pimienta al gusto",
            "1 unidad de cebolla",
            "1 cucharadita de vinagre tinto",
            "2 cucharadas de sillao",
            "4 unidades de papas fritas",
            "perejil picado"
        ],
        "Imagen": [
            "https://cdn.statically.io/img/www.comeperuano.pe/wp-content/uploads/2020/08/receta-vainita-saltada-.jpg?quality=100&f=auto"
        ]
    },
    {
        "Plato": "Tiradito de pescado",
        "Ingrediente": [
            "1/2 kg de pescado perico",
            "jugo de 6 limones",
            "2 choclos sancochados y desgranados",
            "2 camotes amarillos sancochados",
            "1 pizca de culantro picado",
            "1/2 cucharadita de aji limo rojo sin pepas y picado",
            "1 cucharada de sal",
            "1/2 cucharadita de ajo molido",
            "2 cucharadas de ají amarillo licuado"
        ],
        "Imagen": [
            "https://cdn.statically.io/img/www.comeperuano.pe/wp-content/uploads/2020/10/receta-tiradito-de-pescado-1.jpg?quality=100&f=auto"
        ]
    },
    {
        "Plato": "tacu tacu a lo pobre",
        "Ingrediente": [
            "aceite",
            "160 gr de carne sazonado con sal, pimienta y ajo",
            "pan molido",
            "1/4 de cebolla picada",
            "1 cucharadita de ajo molido",
            "2 cucharaditas de ají panca",
            "2 cucharaditas de ají amarillo licuado",
            "140 gr de frejol canario cocido",
            "sal al gusto",
            "pimienta al gusto",
            "comino al gusto",
            "1/8 de taza de caldo de pollo",
            "70 gr de arroz cocido",
            "plátanos fritos",
            "1 huevo frito"
        ],
        "Imagen": [
            "https://cdn.statically.io/img/www.comeperuano.pe/wp-content/uploads/2020/10/receta-tacu-tacu-a-lo-pobre....jpg?quality=100&f=auto"
        ]
    },
    {
        "Plato": "pure de espinaca",
        "Ingrediente": [
            "1 kg papa huamantanga",
            "agua",
            "1 cucharada de aceite",
            "3 cucharada de mantequilla",
            "1 diente de ajo",
            "1 diente de ajo picado",
            "250 gr de hojas de espinaca",
            "400 ml de leche fresca",
            "sal al gusto",
            "pimienta negra al gusto"
        ],
        "Imagen": [
            "https://cdn.statically.io/img/www.comeperuano.pe/wp-content/uploads/2020/10/receta-pure-de-espinaca-1.jpg?quality=100&f=auto"
        ]
    },
    {
        "Plato": "higado frito con yuca",
        "Ingrediente": [
            "300 gr de filete de hígado de res cortado en tiras",
            "sal al gusto",
            "1 cucharada de ajo licuado",
            "2 cucharadas de ají panca",
            "pimienta al gusto",
            "1/2 cucharadita de orégano",
            "comino al gusto",
            "3 cucharadas de vinagre",
            "6 cucharadas de cerveza negra",
            "3 cucharadas de aceite",
            "yucas sancochadas picadas en trozos"
        ],
        "Imagen": [
            "https://cdn.statically.io/img/www.comeperuano.pe/wp-content/uploads/2020/10/receta-higado-con-yuca.jpg?quality=100&f=auto"
        ]
    },
    {
        "Plato": "higado encebollado",
        "Ingrediente": [
            "3 cucharadas de pasta ají panca",
            "400 gr de hígado de res",
            "3 cucharadas vinagre blanco",
            "1/2 taza de cerveza negra",
            "comino al gusto",
            "1 cucharada de ajo picado",
            "sal al gusto",
            "pimienta al gusto",
            "1 cucharadita de orégano",
            "1 ají amarillo sin venas ni pepas cortado en tiras",
            "1 cebolla en gajos",
            "aceite"
        ],
        "Imagen": [
            "https://cdn.statically.io/img/www.comeperuano.pe/wp-content/uploads/2020/10/receta-higado-encebollado...jpg?quality=100&f=auto"
        ]
    },
    {
        "Plato": "Higado apanado",
        "Ingrediente": [
            "2 hígados de res",
            "comino al gusto",
            "1 cucharada de ajo molido",
            "sal al gusto",
            "10 galletas soda molidas"
        ],
        "Imagen": [
            "https://cdn.statically.io/img/www.comeperuano.pe/wp-content/uploads/2020/10/receta-Higado-apanado...jpg?quality=100&f=auto"
        ]
    },
    {
        "Plato": "Ocopa",
        "Ingrediente": [
            "10 ajíes mirasol tostados",
            "½ cebolla roja picada",
            "un diente de ajo",
            "Huacatay cocido",
            "un chorro de Aceite",
            "un chorro de agua",
            "¼ de maní tostado",
            "Galleta de vainilla",
            "Queso fresco",
            "sal",
            "Un chorro de leche"
        ],
        "Imagen": [
            "https://cdn.statically.io/img/www.comeperuano.pe/wp-content/uploads/2020/03/ocopa11.jpg?quality=100&f=auto"
        ]
    },
    {
        "Plato": "Causa rellena",
        "Ingrediente": [
            "agua",
            "papa amarilla",
            "sal",
            "aceite",
            "ají amarillo licuado",
            "limón"
        ],
        "Imagen": [
            "https://cdn.statically.io/img/www.comeperuano.pe/wp-content/uploads/2020/03/CAUSA-RELLENA-1.jpg?quality=100&f=auto"
        ]
    },
    {
        "Plato": "Yuca frita",
        "Ingrediente": [
            "1 yuca amarilla",
            "agua",
            "aceite"
        ],
        "Imagen": [
            "https://cdn.statically.io/img/www.comeperuano.pe/wp-content/uploads/2020/05/receta-yuca-frita....jpg?quality=100&f=auto"
        ]
    },
    {
        "Plato": "papa a la huancaina",
        "Ingrediente": [
            "5 ajíes amarillos frescos",
            "1 tza de queso fresco",
            "1 diente de ajo",
            "1 pisca de leche",
            "Aceite",
            "1kg de papa Huayro",
            "4 aceitunas",
            "Lechuga",
            "1 huevo sancochado",
            "sal al gusto"
        ],
        "Imagen": [
            "https://cdn.statically.io/img/www.comeperuano.pe/wp-content/uploads/2019/05/Papa-a-la-huancayna-receta-peruana.jpg?quality=100&f=auto"
        ]
    },
    {
        "Plato": "crema de rocoto",
        "Ingrediente": [
            "1 rocoto sancochado sin cascara y sin venas",
            "100 gr de queso fresco en trozos",
            "1/2 paquete de galleta soda",
            "1/4 de taza de leche",
            "sal",
            "1 chorro de aceite de oliva"
        ],
        "Imagen": [
            "https://cdn.statically.io/img/www.comeperuano.pe/wp-content/uploads/2020/08/receta-crema-de-rocoto.jpg?quality=100&f=auto"
        ]
    },
    {
        "Plato": "causa de atun",
        "Ingrediente": [
            "500 gr de papa amarilla prensada",
            "3 cucharadas de aceite vegetal",
            "3 cucharadas de pasta de ají amarillo",
            "3 cucharadas de zumo de limón",
            "sal al gusto",
            "1 cebolla picada",
            "1 diente de ajo picado",
            "1 lata de atún",
            "1 cucharada de mayonesa casera o mayonesa de fabrica",
            "pimienta al gusto"
        ],
        "Imagen": [
            "https://cdn.statically.io/img/www.comeperuano.pe/wp-content/uploads/2020/09/receta-causa-de-atun.jpg?quality=100&f=auto"
        ]
    },
    {
        "Plato": "Seco de res",
        "Ingrediente": [
            "1 kg de Trozos de carne",
            "aceite",
            "2 cebollas rojas picadas",
            "ajo molido",
            "½ taza de ají amarillo licuado",
            "½ taza de ají mirasol licuado",
            "chicha de jora o cerveza rubia",
            "culantro licuado",
            "sal",
            "pimiento",
            "comino",
            "agua",
            "1 taza de arvejas crudas",
            "2 zanahorias crudas cortadas en rodajas",
            "4 papas cortadas en dos"
        ],
        "Imagen": [
            "https://cdn.statically.io/img/www.comeperuano.pe/wp-content/uploads/2020/03/seco-de-res-peruano.jpg?quality=100&f=auto"
        ]
    },
    {
        "Plato": "Locro de zapallo",
        "Ingrediente": [
            "Aceite",
            "Cebolla roja picada",
            "Ajo molido",
            "ají amarillo licuado",
            "zapallo picado",
            "Caldo de verduras o agua",
            "Habas cocidas",
            "papas peladas",
            "Choclo cocido",
            "sal",
            "pimienta blanca",
            "comino",
            "palillo",
            "huacatay picado",
            "leche evaporada",
            "queso fresco rallado",
            "huevos pasados o fritos",
            "tiras de ají amarillo",
            "rodaja de rocoto"
        ],
        "Imagen": [
            "https://cdn.statically.io/img/www.comeperuano.pe/wp-content/uploads/2020/03/locro-web2.jpg?quality=100&f=auto"
        ]
    },
    {
        "Plato": "Pollo al horno",
        "Ingrediente": [
            "pollo",
            "sal",
            "Azúcar",
            "pimienta blanca",
            "ajo molido",
            "comino",
            "mostaza",
            "romero",
            "ají mirasol licuado",
            "cerveza",
            "agua",
            "papas",
            "mantequilla"
        ],
        "Imagen": [
            "https://cdn.statically.io/img/www.comeperuano.pe/wp-content/uploads/2020/03/pollo-al-horno12.jpg?quality=100&f=auto"
        ]
    },
    {
        "Plato": "Aji de gallina",
        "Ingrediente": [
            "2 cucharadas de aceite vegetal",
            "1 tz de cebolla roja picada",
            "1 cucharada de ajo molido",
            "¼ de tz de pasta de ají mirasol",
            "¼ de tz de ají amarillo sin venas ni pepas",
            "1 cucharada de ají panca licuado",
            "2 rebanadas de pan de molde",
            "leche evaporada",
            "1 pechuga de pollo",
            "½ t",
            " de caldo de pollo",
            "sal",
            "pimienta blanca",
            "pecanas molidas",
            "queso parmesano",
            "papas blancas",
            "½ huevo duro",
            "aceituna morada"
        ],
        "Imagen": [
            "https://cdn.statically.io/img/www.comeperuano.pe/wp-content/uploads/2020/03/aji-de-gallina-1.jpg?quality=100&f=auto"
        ]
    },
    {
        "Plato": "asado de carne peruano",
        "Ingrediente": [
            "1 kilo de carne asado pejerrey",
            "1 cebolla blanca y una roja",
            "Ajo molido",
            "Ají panca licuado",
            "1 zanahoria, un pimiento rojo",
            "4 tomates",
            "1 chorro de vino",
            "Laurel, perejil, orégano y comino",
            "Aceite"
        ],
        "Imagen": [
            "https://cdn.statically.io/img/www.comeperuano.pe/wp-content/uploads/2020/03/asado-carne-peruano.jpg?quality=100&f=auto"
        ]
    },
    {
        "Plato": "Chanfainita",
        "Ingrediente": [
            "1 kg de pulmón de res",
            "hierbabuena",
            "aceite",
            "2 cebollas rojas picadas",
            "1 cucharada de ajo molido",
            "1 taza de ají panca licuado",
            "2 cucharadas de ají mirasol licuado",
            "4 papas blancas picadas en dados",
            "sal",
            "orégano en polvo",
            "comino",
            "pimienta",
            "2 rodajas de rocoto",
            "1 puñado de cebolla china picada"
        ],
        "Imagen": [
            "https://cdn.statically.io/img/www.comeperuano.pe/wp-content/uploads/2020/03/chanfainita12.jpg?quality=100&f=auto"
        ]
    },
    {
        "Plato": "Arroz con pollo",
        "Ingrediente": [
            "1 Pollo entero",
            "aceite vegetal",
            "sal",
            "pimienta",
            "1 taza cebolla roja picada",
            "1 cucharada de ajo molido",
            "1 taza ají amarillo licuado",
            "1 vaso de cerveza rubia",
            "½ taza de culantro licuado",
            "½ taza de pimiento rojo picado",
            "1 taza de arvejas crudas",
            "½ de zanahoria cruda cortada en forma de dados",
            "½ taza de Choclo desgranado crudo",
            "1 ají amarillo cortado en tiras delgadas",
            "3 tazas de caldo",
            "2 tazas de arroz crudo"
        ],
        "Imagen": [
            "https://cdn.statically.io/img/www.comeperuano.pe/wp-content/uploads/2020/03/arroz-con-pollo11.jpg?quality=100&f=auto"
        ]
    },
    {
        "Plato": "Ensalada rusa",
        "Ingrediente": [
            "2 tazas papas blancas",
            "1 taza de arvejas",
            "1 taza de vainitas",
            "1 taza de zanahoria",
            "2 tazas de betarraga",
            "2 tazas de mayonesa",
            "6 huevos duros",
            "atún",
            "perejil picado",
            "aceituna verde"
        ],
        "Imagen": [
            "https://cdn.statically.io/img/www.comeperuano.pe/wp-content/uploads/2020/03/ensalada-rusa22.jpg?quality=100&f=auto"
        ]
    },
    {
        "Plato": "Tallarines saltados",
        "Ingrediente": [
            "4 piernas de Pollo",
            "aceite",
            "fideos",
            "4 tomate en tiras",
            "2 cebolla rojas en tiras",
            "1 cucharada de ajo molido",
            "1 ají en tiras",
            "2 cabezas de cebolla china",
            "pimienta",
            "comino",
            "vinagre",
            "sillao",
            "1 cucharada de salsa de ostion",
            "culantro",
            "ají limo"
        ],
        "Imagen": [
            "https://cdn.statically.io/img/www.comeperuano.pe/wp-content/uploads/2020/03/RECETA-TALLARIN-SALTADO..jpg?quality=100&f=auto"
        ]
    },
    {
        "Plato": "tallarines verdes",
        "Ingrediente": [
            "400 gramos de pasta",
            "150 gramos de espinacas",
            "70 gramos de albahaca licuadas",
            "3 cdas. de cebolla finamente picada en cuadritos",
            "1 cdta. de ajos molidos",
            "1 pizca de comino",
            "75 gr de queso fresco",
            "1/4 de taza de leche evaporada",
            "25 gramos de nueces, almendras o pecanas",
            "Sal y pimienta al gusto",
            "Aceite de oliva o vegetal"
        ],
        "Imagen": [
            "https://jameaperu.com/wp-content/uploads/2018/12/tallarines-verdes_700x465.jpg"
        ]
    },
    {
        "Plato": "Arroz con chancho",
        "Ingrediente": [
            "Panceta de cerdo cortada en trozos medianos de 30 gr",
            "Sal",
            "Pimienta",
            "Agua",
            "Ajo molido",
            "Cebolla picada",
            "Ají amarillo licuado",
            "1 cucharada de palillo",
            "1 taza de culantro picado",
            "1 taza de hierbabuena picada",
            "1 taza de perejil picada",
            "1 botella de cerveza",
            "1/2 taza de nabo pelado y picado en cubos chicos",
            "1/2 taza de camote pelado y picado en cubos",
            "1/2 taza de fréjol tierno pelado",
            "1/2 taza de arvejas tiernas",
            "1/2 taza de pimiento rojo picado",
            "1 ají amarillo cortado en tiras",
            "2 tazas de arroz largo",
            "1 taza de col picada"
        ],
        "Imagen": [
            "https://cdn.statically.io/img/www.comeperuano.pe/wp-content/uploads/2020/05/receta-arroz-con-chancho.jpg?quality=100&f=auto"
        ]
    },
    {
        "Plato": "escabeche de pollo",
        "Ingrediente": [
            "5 encuentros de pollo sin piel y desgrasados",
            "700 gr de cebolla roja",
            "3 cdas de ají amarillo molido",
            "2 ajies amarillos enteros",
            "2 cdas de aji panca",
            "1/2 tasa de vinagre de vino tinto",
            "1 pisca de comino",
            "1/4 cdta de pimienta",
            "1/2 cdta de orégano",
            "sal al gusto",
            "Aceite vegetal.",
            "Ramitas de canela",
            "Aceite de achiote"
        ],
        "Imagen": [
            "https://cdn.statically.io/img/www.comeperuano.pe/wp-content/uploads/2020/06/Escabeche-de-pollo-peruano.jpg?quality=100&f=auto"
        ]
    },
    {
        "Plato": "papa rellena",
        "Ingrediente": [
            "1 ½ de papa rosada",
            "1 huevo",
            "1/4 de cdta. de pimienta",
            "Sal al gusto",
            "350 gr. de carne de res picada, de preferencia lomo o cadera",
            "1 y 1/2 tazas de cebolla picada en cuadritos",
            "2 dientes de ajo molidos",
            "1 cda. de ají amarillo cortado en cuadritos",
            "1 cda. de perejil finamente picado",
            "1 cda. de ají panca molido o ají especial",
            "1/4 de cdta. de pimienta",
            "1 pizca de comino",
            "1/4 de cdta. de orégano",
            "Sal al gusto",
            "1/4 de taza de pasas hidratadas en agua",
            "Aceitunas negras de botija",
            "2 huevos",
            "Un chorrito de aceite vegetal",
            "3/4 de taza de harina de trigo",
            "2 huevos",
            "Aceite vegetal"
        ],
        "Imagen": [
            "https://cdn.statically.io/img/www.comeperuano.pe/wp-content/uploads/2020/04/receta-papa-rellena.jpg?quality=100&f=auto"
        ]
    },
    {
        "Plato": "cau cau",
        "Ingrediente": [
            "1 1/2 kg de mondongo",
            "1 cda de ajo molido",
            "1 tza de cebolla roja picada",
            "1 tza de aji amarillo licuado",
            "sal, pimienta blanca, comino y palillo al gusto."
        ],
        "Imagen": [
            "https://cdn.statically.io/img/www.comeperuano.pe/wp-content/uploads/2019/06/receta-casera-cau-cau.jpg?quality=100&f=auto"
        ]
    },
    {
        "Plato": "Cabrito a la norteña",
        "Ingrediente": [
            "04 piezas de cabrito",
            "02 cebollas en cuadritos",
            "02 cucharadas de ajonjolí",
            "01 cucharada de comino",
            "02 cucharadas de ají panca molido",
            "1/2 taza de ají mirasol molido",
            "01 taza de zapallo loche con cáscara",
            "02 cucharadas de cilantro picado",
            "04 porciones de yuca sancochada",
            "1/2 taza de ají amarillo molido",
            "04 ramas de culantro",
            "04 cucharadas de culantro picado",
            "1/2 botella de chicha de jora",
            "04 cucharadas de aceite vegetal",
            "1/2 cucharada de pimienta",
            "Sal al gusto"
        ],
        "Imagen": [
            "https://cdn.statically.io/img/www.comeperuano.pe/wp-content/uploads/2020/08/receta-cabrito-a-la-norteña.jpg?quality=100&f=auto"
        ]
    },
    {
        "Plato": "Bistec a lo pobre",
        "Ingrediente": [
            "3 papas blancas cortadas en bastones",
            "aceite vegetal",
            "2 filetes de carne de res",
            "2 huevos fritos",
            "sal",
            "1/2 cucharadita de ajo molido",
            "1 pizca de pimienta",
            "1 pizca de comino",
            "1 pizca de orégano",
            "1 cucharadita de vinagre tinto",
            "2 plátanos bellacos maduros cortados de forma larga"
        ],
        "Imagen": [
            "https://cdn.statically.io/img/www.comeperuano.pe/wp-content/uploads/2020/10/receta-bistec-a-lo-pobre.jpg?quality=100&f=auto"
        ]
    }
]